weconnect_mqtt/__init__.py
weconnect_mqtt/__main__.py
weconnect_mqtt/__version.py
weconnect_mqtt/weconnect_mqtt_base.py
weconnect_mqtt-0.49.2.dist-info/LICENSE
weconnect_mqtt-0.49.2.dist-info/METADATA
weconnect_mqtt-0.49.2.dist-info/WHEEL
weconnect_mqtt-0.49.2.dist-info/entry_points.txt
weconnect_mqtt-0.49.2.dist-info/top_level.txt
weconnect_mqtt-0.49.2.dist-info/RECORD
