Metadata-Version: 2.1
Name: weconnect-mqtt
Version: 0.49.2
Summary: MQTT Client that publishes data from Volkswagen WeConnect
Home-page: https://github.com/tillsteinbach/WeConnect-mqtt
Author: Till Steinbach
License: MIT
Project-URL: Funding, https://github.com/sponsors/WeConnect-mqtt
Project-URL: Source, https://github.com/tillsteinbach/WeConnect-mqtt
Project-URL: Bug Tracker, https://github.com/tillsteinbach/WeConnect-mqtt/issues
Keywords: weconnect,we connect,carnet,car net,volkswagen,vw,telemetry,mqtt,smarthome
Classifier: Development Status :: 3 - Alpha
Classifier: Environment :: Console
Classifier: License :: OSI Approved :: MIT License
Classifier: Intended Audience :: End Users/Desktop
Classifier: Intended Audience :: System Administrators
Classifier: Programming Language :: Python :: 3.8
Classifier: Programming Language :: Python :: 3.9
Classifier: Programming Language :: Python :: 3.10
Classifier: Programming Language :: Python :: 3.11
Classifier: Programming Language :: Python :: 3.12
Classifier: Topic :: Utilities
Classifier: Topic :: System :: Monitoring
Classifier: Topic :: Home Automation
Requires-Python: >=3.8
License-File: LICENSE
Requires-Dist: weconnect[images]~=0.60.5
Requires-Dist: paho-mqtt~=2.1.0
Requires-Dist: python-dateutil~=2.9.0
